cakeme/__init__.py
cakeme/applibase.py
cakeme/fileutiles.py
cakeme/fileutils.py
cakeme/greet.py
cakeme-0.0.4.dist-info/DESCRIPTION.rst
cakeme-0.0.4.dist-info/METADATA
cakeme-0.0.4.dist-info/RECORD
cakeme-0.0.4.dist-info/WHEEL
cakeme-0.0.4.dist-info/metadata.json
cakeme-0.0.4.dist-info/top_level.txt
