Metadata-Version: 2.0
Name: cakeme
Version: 0.0.4
Summary: cook up a call to a third party application
Home-page: UNKNOWN
Author: Witold Wolski
Author-email: wolski@gmail.com
License: BSD
Platform: UNKNOWN
